{
  "id": "5fe5c9fe9712e25abb1e299f",
  "name": "Producer",
  "description": "Tasty Cheese d12f9167-4e85-4f4d-8b96-4de0bfcfb367",
  "labels": [
      "neural",
      "Account",
      "Hampshire"
  ],
  "tests": [
      {
        "id": "5fe5cb079712e25abb1e2bd5",
        "key": "5fe5cb079712e25abb1e2bd6",
        "name": "Berkshire",
        "labels": [
            "grey"
        ],
        "status": "failed"
      },
      {
        "id": "5fe5cb079712e25abb1e2bd7",
        "key": "5fe5cb079712e25abb1e2bd8",
        "name": "Cambridgeshire",
        "labels": [
            "Burgs"
        ],
        "status": "unknown"
      },
      {
        "id": "5fe5cb079712e25abb1e2bd9",
        "key": "5fe5cb079712e25abb1e2bda",
        "name": "Mouse action-items Optional",
        "labels": [
            "matrix",
            "Refined"
        ],
        "status": "unknown"
      },
      {
        "id": "5fe5cb079712e25abb1e2bdb",
        "key": "5fe5cb079712e25abb1e2bdc",
        "name": "partnerships responsive",
        "labels": [
            "Personal",
            "open-source",
            "Virginia"
        ],
        "status": "unknown"
      },
      {
        "id": "5fe5cb079712e25abb1e2bdd",
        "key": "5fe5cb079712e25abb1e2bde",
        "name": "Indiana neutral Cambridgeshire",
        "labels": [
        ],
        "status": "passed"
      },
      {
        "id": "5fe5cb079712e25abb1e2bdf",
        "key": "5fe5cb079712e25abb1e2be0",
        "name": "Regional PCI Account",
        "labels": [
        ],
        "status": "failed"
      },
      {
        "id": "5fe5cb079712e25abb1e2be1",
        "key": "5fe5cb079712e25abb1e2be2",
        "name": "network Directives",
        "labels": [
            "global",
            "virtual"
        ],
        "status": "unknown"
      },
      {
        "id": "5fe5cb079712e25abb1e2be3",
        "key": "5fe5cb079712e25abb1e2be4",
        "name": "rich",
        "labels": [
            "Islands"
        ],
        "status": "failed"
      },
      {
        "id": "5fe5cb079712e25abb1e2be5",
        "key": "5fe5cb079712e25abb1e2be6",
        "name": "Self-enabling Loan",
        "labels": [
            "SMS",
            "fuchsia"
        ],
        "status": "passed"
      },
      {
        "id": "5fe5cb079712e25abb1e2be7",
        "key": "5fe5cb079712e25abb1e2be8",
        "name": "optical Account",
        "labels": [
            "back-end",
            "Steel",
            "archive"
        ],
        "status": "unknown"
      },
      {
        "id": "5fe5cb079712e25abb1e2be9",
        "key": "5fe5cb079712e25abb1e2bea",
        "name": "analyzing",
        "labels": [
            "index"
        ],
        "status": "failed"
      },
      {
        "id": "5fe5cb079712e25abb1e2beb",
        "key": "5fe5cb079712e25abb1e2bec",
        "name": "Directives",
        "labels": [
            "Marketing",
            "AI"
        ],
        "status": "failed"
      },
      {
        "id": "5fe5cb079712e25abb1e2bed",
        "key": "5fe5cb079712e25abb1e2bee",
        "name": "Bacon revolutionize optical",
        "labels": [
            "holistic",
            "connecting",
            "Granite"
        ],
        "status": "unknown"
      },
      {
        "id": "5fe5cb079712e25abb1e2bef",
        "key": "5fe5cb079712e25abb1e2bf0",
        "name": "Grocery program",
        "labels": [
            "orange"
        ],
        "status": "failed"
      },
      {
        "id": "5fe5cb079712e25abb1e2bf1",
        "key": "5fe5cb079712e25abb1e2bf2",
        "name": "generate",
        "labels": [
        ],
        "status": "failed"
      },
      {
        "id": "5fe5cb079712e25abb1e2bf3",
        "key": "5fe5cb079712e25abb1e2bf4",
        "name": "Games Implementation",
        "labels": [
        ],
        "status": "unknown"
      },
      {
        "id": "5fe5cb079712e25abb1e2bf5",
        "key": "5fe5cb079712e25abb1e2bf6",
        "name": "Fantastic Dollar",
        "labels": [
            "Gloves"
        ],
        "status": "unknown"
      },
      {
        "id": "5fe5cb079712e25abb1e2bf7",
        "key": "5fe5cb079712e25abb1e2bf8",
        "name": "blue",
        "labels": [
            "Towels",
            "sensor",
            "Colorado"
        ],
        "status": "passed"
      },
      {
        "id": "5fe5cb079712e25abb1e2bf9",
        "key": "5fe5cb079712e25abb1e2bfa",
        "name": "Peso Open-source Tasty",
        "labels": [
            "Salad",
            "Business-focused",
            "system"
        ],
        "status": "unknown"
      },
      {
        "id": "5fe5cb079712e25abb1e2bfb",
        "key": "5fe5cb079712e25abb1e2bfc",
        "name": "Account Multi-channelled",
        "labels": [
            "card"
        ],
        "status": "failed"
      },
      {
        "id": "5fe5cb079712e25abb1e2bfd",
        "key": "5fe5cb079712e25abb1e2bfe",
        "name": "budgetary",
        "labels": [
            "synthesize",
            "Intelligent",
            "mindshare"
        ],
        "status": "failed"
      },
      {
        "id": "5fe5cb079712e25abb1e2bff",
        "key": "5fe5cb079712e25abb1e2c00",
        "name": "Car",
        "labels": [
            "Games",
            "connecting"
        ],
        "status": "passed"
      },
      {
        "id": "5fe5cb079712e25abb1e2c01",
        "key": "5fe5cb079712e25abb1e2c02",
        "name": "application",
        "labels": [
        ],
        "status": "unknown"
      },
      {
        "id": "5fe5cb079712e25abb1e2c03",
        "key": "5fe5cb079712e25abb1e2c04",
        "name": "Chips Tools",
        "labels": [
            "redundant",
            "Granite",
            "Interface"
        ],
        "status": "failed"
      },
      {
        "id": "5fe5cb079712e25abb1e2c05",
        "key": "5fe5cb079712e25abb1e2c06",
        "name": "feed responsive Intelligent",
        "labels": [
            "programming"
        ],
        "status": "failed"
      },
      {
        "id": "5fe5cb079712e25abb1e2c07",
        "key": "5fe5cb079712e25abb1e2c08",
        "name": "Supervisor payment",
        "labels": [
            "Saint"
        ],
        "status": "passed"
      },
      {
        "id": "5fe5cb079712e25abb1e2c09",
        "key": "5fe5cb079712e25abb1e2c0a",
        "name": "copying generating",
        "labels": [
            "architect",
            "web-readiness"
        ],
        "status": "failed"
      },
      {
        "id": "5fe5cb079712e25abb1e2c0b",
        "key": "5fe5cb079712e25abb1e2c0c",
        "name": "synthesize",
        "labels": [
            "Table",
            "Frozen"
        ],
        "status": "failed"
      },
      {
        "id": "5fe5cb079712e25abb1e2c0d",
        "key": "5fe5cb079712e25abb1e2c0e",
        "name": "Rwanda Tala",
        "labels": [
        ],
        "status": "failed"
      },
      {
        "id": "5fe5cb079712e25abb1e2c0f",
        "key": "5fe5cb079712e25abb1e2c10",
        "name": "Directives budgetary auxiliary",
        "labels": [
            "Loan"
        ],
        "status": "passed"
      },
      {
        "id": "5fe5cb079712e25abb1e2c11",
        "key": "5fe5cb079712e25abb1e2c12",
        "name": "Berkshire brand",
        "labels": [
        ],
        "status": "failed"
      },
      {
        "id": "5fe5cb079712e25abb1e2c13",
        "key": "5fe5cb079712e25abb1e2c14",
        "name": "context-sensitive parsing Books",
        "labels": [
            "Lead",
            "Marketing",
            "auxiliary"
        ],
        "status": "passed"
      },
      {
        "id": "5fe5cb079712e25abb1e2c15",
        "key": "5fe5cb079712e25abb1e2c16",
        "name": "Toys",
        "labels": [
            "upward-trending"
        ],
        "status": "passed"
      },
      {
        "id": "5fe5cb079712e25abb1e2c17",
        "key": "5fe5cb079712e25abb1e2c18",
        "name": "Diverse bandwidth",
        "labels": [
            "Executive",
            "Account",
            "Salad"
        ],
        "status": "passed"
      },
      {
        "id": "5fe5cb079712e25abb1e2c19",
        "key": "5fe5cb079712e25abb1e2c1a",
        "name": "target Central firewall",
        "labels": [
            "withdrawal"
        ],
        "status": "unknown"
      },
      {
        "id": "5fe5cb079712e25abb1e2c1b",
        "key": "5fe5cb079712e25abb1e2c1c",
        "name": "Cameroon backing",
        "labels": [
        ],
        "status": "passed"
      },
      {
        "id": "5fe5cb079712e25abb1e2c1d",
        "key": "5fe5cb079712e25abb1e2c1e",
        "name": "deposit",
        "labels": [
            "tan"
        ],
        "status": "failed"
      },
      {
        "id": "5fe5cb079712e25abb1e2c1f",
        "key": "5fe5cb079712e25abb1e2c20",
        "name": "New Kentucky drive",
        "labels": [
        ],
        "status": "failed"
      },
      {
        "id": "5fe5cb079712e25abb1e2c21",
        "key": "5fe5cb079712e25abb1e2c22",
        "name": "transmitting Mouse",
        "labels": [
            "Internal",
            "navigating"
        ],
        "status": "passed"
      },
      {
        "id": "5fe5cb079712e25abb1e2c23",
        "key": "5fe5cb079712e25abb1e2c24",
        "name": "Specialist",
        "labels": [
        ],
        "status": "failed"
      },
      {
        "id": "5fe5cb079712e25abb1e2c25",
        "key": "5fe5cb079712e25abb1e2c26",
        "name": "generating",
        "labels": [
            "Kentucky"
        ],
        "status": "failed"
      },
      {
        "id": "5fe5cb079712e25abb1e2c27",
        "key": "5fe5cb079712e25abb1e2c28",
        "name": "maximized cross-media Way",
        "labels": [
            "system",
            "users"
        ],
        "status": "passed"
      },
      {
        "id": "5fe5cb079712e25abb1e2c29",
        "key": "5fe5cb079712e25abb1e2c2a",
        "name": "Dominican Gold RAM",
        "labels": [
            "Intranet",
            "calculating",
            "Sausages"
        ],
        "status": "unknown"
      },
      {
        "id": "5fe5cb079712e25abb1e2c2b",
        "key": "5fe5cb079712e25abb1e2c2c",
        "name": "Cape HTTP Markets",
        "labels": [
        ],
        "status": "failed"
      },
      {
        "id": "5fe5cb079712e25abb1e2c2d",
        "key": "5fe5cb079712e25abb1e2c2e",
        "name": "Group",
        "labels": [
        ],
        "status": "unknown"
      },
      {
        "id": "5fe5cb079712e25abb1e2c2f",
        "key": "5fe5cb079712e25abb1e2c30",
        "name": "Indiana Handcrafted",
        "labels": [
            "backing"
        ],
        "status": "passed"
      },
      {
        "id": "5fe5cb079712e25abb1e2c31",
        "key": "5fe5cb079712e25abb1e2c32",
        "name": "New Kansas",
        "labels": [
            "Syrian",
            "primary"
        ],
        "status": "unknown"
      },
      {
        "id": "5fe5cb079712e25abb1e2c33",
        "key": "5fe5cb079712e25abb1e2c34",
        "name": "Steel Frozen Intelligent",
        "labels": [
        ],
        "status": "passed"
      },
      {
        "id": "5fe5cb079712e25abb1e2c35",
        "key": "5fe5cb079712e25abb1e2c36",
        "name": "Metrics Shirt Arizona",
        "labels": [
            "invoice",
            "grey",
            "Rupiah"
        ],
        "status": "passed"
      },
      {
        "id": "5fe5cb079712e25abb1e2c37",
        "key": "5fe5cb079712e25abb1e2c38",
        "name": "Books optimal",
        "labels": [
            "Tactics"
        ],
        "status": "failed"
      },
      {
        "id": "5fe5cb079712e25abb1e2c39",
        "key": "5fe5cb079712e25abb1e2c3a",
        "name": "e-tailers",
        "labels": [
        ],
        "status": "failed"
      },
      {
        "id": "5fe5cb079712e25abb1e2c3b",
        "key": "5fe5cb079712e25abb1e2c3c",
        "name": "primary",
        "labels": [
            "functionalities",
            "parsing",
            "multi-byte"
        ],
        "status": "passed"
      },
      {
        "id": "5fe5cb079712e25abb1e2c3d",
        "key": "5fe5cb079712e25abb1e2c3e",
        "name": "Reduced drive GB",
        "labels": [
            "concept",
            "Cambridgeshire",
            "Investment"
        ],
        "status": "failed"
      },
      {
        "id": "5fe5cb079712e25abb1e2c3f",
        "key": "5fe5cb079712e25abb1e2c40",
        "name": "Sudan Clothing orchid",
        "labels": [
            "bus",
            "fuchsia",
            "Rubber"
        ],
        "status": "failed"
      },
      {
        "id": "5fe5cb079712e25abb1e2c41",
        "key": "5fe5cb079712e25abb1e2c42",
        "name": "Utah",
        "labels": [
        ],
        "status": "failed"
      },
      {
        "id": "5fe5cb079712e25abb1e2c43",
        "key": "5fe5cb079712e25abb1e2c44",
        "name": "Plastic optical application",
        "labels": [
        ],
        "status": "unknown"
      },
      {
        "id": "5fe5cb079712e25abb1e2c45",
        "key": "5fe5cb079712e25abb1e2c46",
        "name": "navigating",
        "labels": [
            "e-enable"
        ],
        "status": "passed"
      },
      {
        "id": "5fe5cb079712e25abb1e2c47",
        "key": "5fe5cb079712e25abb1e2c48",
        "name": "violet",
        "labels": [
            "leading-edge",
            "lavender"
        ],
        "status": "passed"
      },
      {
        "id": "5fe5cb079712e25abb1e2c49",
        "key": "5fe5cb079712e25abb1e2c4a",
        "name": "monetize tan payment",
        "labels": [
            "Small"
        ],
        "status": "unknown"
      },
      {
        "id": "5fe5cb079712e25abb1e2c4b",
        "key": "5fe5cb079712e25abb1e2c4c",
        "name": "Taiwan",
        "labels": [
            "protocol"
        ],
        "status": "passed"
      },
      {
        "id": "5fe5cb079712e25abb1e2c4d",
        "key": "5fe5cb079712e25abb1e2c4e",
        "name": "Road hack",
        "labels": [
            "niches"
        ],
        "status": "failed"
      },
      {
        "id": "5fe5cb079712e25abb1e2c4f",
        "key": "5fe5cb079712e25abb1e2c50",
        "name": "Pants COM",
        "labels": [
            "Union"
        ],
        "status": "passed"
      },
      {
        "id": "5fe5cb079712e25abb1e2c51",
        "key": "5fe5cb079712e25abb1e2c52",
        "name": "Open-source Fresh",
        "labels": [
            "discrete",
            "Florida"
        ],
        "status": "passed"
      },
      {
        "id": "5fe5cb079712e25abb1e2c53",
        "key": "5fe5cb079712e25abb1e2c54",
        "name": "deliver transitional",
        "labels": [
        ],
        "status": "unknown"
      },
      {
        "id": "5fe5cb079712e25abb1e2c55",
        "key": "5fe5cb079712e25abb1e2c56",
        "name": "deposit",
        "labels": [
            "California",
            "Executive"
        ],
        "status": "failed"
      },
      {
        "id": "5fe5cb079712e25abb1e2c57",
        "key": "5fe5cb079712e25abb1e2c58",
        "name": "dynamic",
        "labels": [
            "Account",
            "Netherlands",
            "transitional"
        ],
        "status": "passed"
      },
      {
        "id": "5fe5cb079712e25abb1e2c59",
        "key": "5fe5cb079712e25abb1e2c5a",
        "name": "index redundant Outdoors",
        "labels": [
            "Investment",
            "Loan"
        ],
        "status": "failed"
      },
      {
        "id": "5fe5cb079712e25abb1e2c5b",
        "key": "5fe5cb079712e25abb1e2c5c",
        "name": "Caribbean strategy",
        "labels": [
            "Toys"
        ],
        "status": "failed"
      },
      {
        "id": "5fe5cb079712e25abb1e2c5d",
        "key": "5fe5cb079712e25abb1e2c5e",
        "name": "array",
        "labels": [
            "JBOD"
        ],
        "status": "unknown"
      },
      {
        "id": "5fe5cb079712e25abb1e2c5f",
        "key": "5fe5cb079712e25abb1e2c60",
        "name": "up Lempira",
        "labels": [
            "haptic"
        ],
        "status": "unknown"
      },
      {
        "id": "5fe5cb079712e25abb1e2c61",
        "key": "5fe5cb079712e25abb1e2c62",
        "name": "array azure haptic",
        "labels": [
        ],
        "status": "unknown"
      },
      {
        "id": "5fe5cb079712e25abb1e2c63",
        "key": "5fe5cb079712e25abb1e2c64",
        "name": "quantifying",
        "labels": [
        ],
        "status": "passed"
      },
      {
        "id": "5fe5cb079712e25abb1e2c65",
        "key": "5fe5cb079712e25abb1e2c66",
        "name": "Uzbekistan Product",
        "labels": [
            "Pizza",
            "Account"
        ],
        "status": "failed"
      },
      {
        "id": "5fe5cb079712e25abb1e2c67",
        "key": "5fe5cb079712e25abb1e2c68",
        "name": "Virginia Keyboard Internal",
        "labels": [
            "synthesizing"
        ],
        "status": "unknown"
      },
      {
        "id": "5fe5cb079712e25abb1e2c69",
        "key": "5fe5cb079712e25abb1e2c6a",
        "name": "functionalities Cotton",
        "labels": [
            "Bedfordshire",
            "infrastructure"
        ],
        "status": "failed"
      },
      {
        "id": "5fe5cb079712e25abb1e2c6b",
        "key": "5fe5cb079712e25abb1e2c6c",
        "name": "Bolivia",
        "labels": [
            "Belarussian",
            "Salad",
            "Sausages"
        ],
        "status": "failed"
      },
      {
        "id": "5fe5cb079712e25abb1e2c6d",
        "key": "5fe5cb079712e25abb1e2c6e",
        "name": "Handmade",
        "labels": [
            "Carolina"
        ],
        "status": "failed"
      },
      {
        "id": "5fe5cb079712e25abb1e2c6f",
        "key": "5fe5cb079712e25abb1e2c70",
        "name": "Bhutanese",
        "labels": [
        ],
        "status": "unknown"
      },
      {
        "id": "5fe5cb079712e25abb1e2c71",
        "key": "5fe5cb079712e25abb1e2c72",
        "name": "SQL",
        "labels": [
            "Lead",
            "Georgia",
            "Zealand"
        ],
        "status": "passed"
      },
      {
        "id": "5fe5cb079712e25abb1e2c73",
        "key": "5fe5cb079712e25abb1e2c74",
        "name": "copy",
        "labels": [
        ],
        "status": "failed"
      },
      {
        "id": "5fe5cb079712e25abb1e2c75",
        "key": "5fe5cb079712e25abb1e2c76",
        "name": "Gorgeous applications",
        "labels": [
            "open"
        ],
        "status": "failed"
      },
      {
        "id": "5fe5cb079712e25abb1e2c77",
        "key": "5fe5cb079712e25abb1e2c78",
        "name": "Alley",
        "labels": [
            "Fiji"
        ],
        "status": "failed"
      },
      {
        "id": "5fe5cb079712e25abb1e2c79",
        "key": "5fe5cb079712e25abb1e2c7a",
        "name": "white Heights Technician",
        "labels": [
        ],
        "status": "passed"
      },
      {
        "id": "5fe5cb079712e25abb1e2c7b",
        "key": "5fe5cb079712e25abb1e2c7c",
        "name": "Avon Granite Berkshire",
        "labels": [
            "hack",
            "Games",
            "Divide"
        ],
        "status": "unknown"
      },
      {
        "id": "5fe5cb079712e25abb1e2c7d",
        "key": "5fe5cb079712e25abb1e2c7e",
        "name": "Legacy COM",
        "labels": [
            "Marketing",
            "Investor"
        ],
        "status": "unknown"
      },
      {
        "id": "5fe5cb079712e25abb1e2c7f",
        "key": "5fe5cb079712e25abb1e2c80",
        "name": "GB",
        "labels": [
        ],
        "status": "unknown"
      },
      {
        "id": "5fe5cb079712e25abb1e2c81",
        "key": "5fe5cb079712e25abb1e2c82",
        "name": "synthesizing Optimization Account",
        "labels": [
            "quantify",
            "Marshall"
        ],
        "status": "failed"
      },
      {
        "id": "5fe5cb079712e25abb1e2c83",
        "key": "5fe5cb079712e25abb1e2c84",
        "name": "Industrial Arizona",
        "labels": [
        ],
        "status": "failed"
      },
      {
        "id": "5fe5cb079712e25abb1e2c85",
        "key": "5fe5cb079712e25abb1e2c86",
        "name": "Intelligent",
        "labels": [
            "neural",
            "mission-critical",
            "Libyan"
        ],
        "status": "failed"
      },
      {
        "id": "5fe5cb079712e25abb1e2c87",
        "key": "5fe5cb079712e25abb1e2c88",
        "name": "monitor lime Monitored",
        "labels": [
            "strategize"
        ],
        "status": "failed"
      }
  ]
}